flask_tor/__init__.py
flask_tor/common.py
flask_tor/flask_tor.py
flask_tor/onion.py
flask_tor/onionstart.py
flask_tor/settings.py
flask_tor/torrc_template
flask_tor/torrc_template-windows
flask_tor-1.1.0.dist-info/LICENSE
flask_tor-1.1.0.dist-info/METADATA
flask_tor-1.1.0.dist-info/WHEEL
flask_tor-1.1.0.dist-info/top_level.txt
flask_tor-1.1.0.dist-info/RECORD
