Metadata-Version: 2.1
Name: flask-tor
Version: 1.1.0
Summary: A simple way to run Flask apps on tor from your machine.
Home-page: https://github.com/jakbin/flask-tor
Author: Jak Bin
License: MIT License
Project-URL: Bug Tracker, https://github.com/jakbin/flask-tor/issues
Keywords: flask,tor,onion
Classifier: Development Status :: 4 - Beta
Classifier: Programming Language :: Python :: 3.6
Classifier: License :: OSI Approved :: MIT License
Classifier: Operating System :: OS Independent
Requires-Python: >=3
License-File: LICENSE
Requires-Dist: Flask
Requires-Dist: stem
